<annotation>
    <filename>20240114-150412.jpg</filename>
    <folder>Note-Detection</folder>
    <source>
        <database>Note-Detection</database>
        <annotation>custom</annotation>
        <image>custom</image>
    </source>
    <size>
        <width>640</width>
        <height>480</height>
        <depth>3</depth>
    </size>
    <segmented>0</segmented>
    <object>
        <name>Note</name>
        <pose>unspecified</pose>
        <truncated>0</truncated>
        <difficult>0</difficult>
        <bndbox>
            <xmin>53</xmin>
            <ymin>129</ymin>
            <xmax>281</xmax>
            <ymax>224</ymax>
        </bndbox>
    </object>
    <object>
        <name>Note</name>
        <pose>unspecified</pose>
        <truncated>0</truncated>
        <difficult>0</difficult>
        <bndbox>
            <xmin>218</xmin>
            <ymin>197</ymin>
            <xmax>527</xmax>
            <ymax>359</ymax>
        </bndbox>
    </object>
</annotation>
